{
	"classtype": "kObjectclass",
	"internalversion": 3,
	"superclass": "fhir.FHIRBaseElement",
	"designtaskname": "",
	"cvardefs": [
		{
			"name": "cElements",
			"order": 1,
			"type": "kList",
			"subtype": "",
			"sublen": 0
		},
		{
			"name": "cElementsInited",
			"order": 2,
			"type": "kBoolean",
			"subtype": 0,
			"sublen": 0
		}
	],
	"ivardefs": [
		{
			"name": "coverage",
			"order": 1,
			"type": "kObjectref",
			"subtype": "oReference",
			"sublen": 0,
			"desc": "The party(s) that are responsible for payment (or part of) of charges applied to this account (including self-pay).\n\nA coverage may only be resposible for specific types of charges, and the sequence of the coverages in the account could be important when "
		},
		{
			"name": "priority",
			"order": 2,
			"type": "kInteger",
			"subtype": "k32bitint",
			"sublen": 0,
			"desc": "The priority of the coverage in the context of this account."
		}
	],
	"properties": {
		"collectperformancedata": false,
		"componenticon": 0,
		"componenttype": "kCompStoreHidden",
		"createdate": "2020-06-01 17:39:56",
		"desc": "The party(s) that are responsible for covering the payment of this account, and what order should they be applied to the account.",
		"editor": "",
		"editordata": "",
		"external": true,
		"issupercomponent": false,
		"moddate": "2020-06-01 17:57:26",
		"selfcontained": false,
		"showascheckedout": false,
		"userinfo": "",
		"version": ""
	}
}
