{
	"classtype": "kObjectclass",
	"internalversion": 3,
	"superclass": "fhir.FHIRBaseElement",
	"designtaskname": "",
	"cvardefs": [
		{
			"name": "cElements",
			"order": 1,
			"type": "kList",
			"subtype": "",
			"sublen": 0
		},
		{
			"name": "cElementsInited",
			"order": 2,
			"type": "kBoolean",
			"subtype": 0,
			"sublen": 0
		}
	],
	"ivardefs": [
		{
			"name": "contact",
			"order": 11,
			"type": "kList",
			"subtype": "",
			"sublen": 0
		},
		{
			"name": "contact_",
			"order": 12,
			"type": "kObjectref",
			"subtype": "oContactDetail",
			"sublen": 0,
			"desc": "Contact details to assist a user in finding and communicating with the publisher."
		},
		{
			"name": "copyright",
			"order": 19,
			"type": "kCharacter",
			"subtype": "kSimplechar",
			"sublen": 100000000,
			"desc": "A copyright statement relating to the structure map and/or its contents. Copyright statements are generally legal restrictions on the use and publishing of the structure map."
		},
		{
			"name": "date",
			"order": 9,
			"type": "kDate",
			"subtype": "kDatetime",
			"sublen": 0,
			"desc": "The date  (and optionally time) when the structure map was published. The date must change when the business version changes and it must change if the status code changes. In addition, it should change when the substantive content of the structure map cha"
		},
		{
			"name": "description",
			"order": 13,
			"type": "kCharacter",
			"subtype": "kSimplechar",
			"sublen": 100000000,
			"desc": "A free text natural language description of the structure map from a consumer's perspective."
		},
		{
			"name": "experimental",
			"order": 8,
			"type": "kBoolean",
			"subtype": 0,
			"sublen": 0,
			"desc": "A Boolean value to indicate that this structure map is authored for testing purposes (or education/evaluation/marketing) and is not intended to be used for genuine usage."
		},
		{
			"name": "group",
			"order": 24,
			"type": "kList",
			"subtype": "",
			"sublen": 0
		},
		{
			"name": "group_",
			"order": 25,
			"type": "kObjectref",
			"subtype": "oStructureMapGroup",
			"sublen": 0,
			"desc": "Organizes the mapping into manageable chunks for human review/ease of maintenance."
		},
		{
			"name": "identifier",
			"order": 2,
			"type": "kList",
			"subtype": "",
			"sublen": 0
		},
		{
			"name": "identifier_",
			"order": 3,
			"type": "kObjectref",
			"subtype": "oIdentifier",
			"sublen": 0,
			"desc": "A formal identifier that is used to identify this structure map when it is represented in other formats, or referenced in a specification, model, design or an instance."
		},
		{
			"name": "import",
			"order": 22,
			"type": "kList",
			"subtype": "",
			"sublen": 0
		},
		{
			"name": "import_",
			"order": 23,
			"type": "kCharacter",
			"subtype": "kSimplechar",
			"sublen": 100000000,
			"desc": "Other maps used by this map (canonical URLs)."
		},
		{
			"name": "jurisdiction",
			"order": 16,
			"type": "kList",
			"subtype": "",
			"sublen": 0
		},
		{
			"name": "jurisdiction_",
			"order": 17,
			"type": "kObjectref",
			"subtype": "oCodeableConcept",
			"sublen": 0,
			"desc": "A legal or geographic region in which the structure map is intended to be used."
		},
		{
			"name": "name",
			"order": 5,
			"type": "kCharacter",
			"subtype": "kSimplechar",
			"sublen": 100000000,
			"desc": "A natural language name identifying the structure map. This name should be usable as an identifier for the module by machine processing applications such as code generation."
		},
		{
			"name": "publisher",
			"order": 10,
			"type": "kCharacter",
			"subtype": "kSimplechar",
			"sublen": 100000000,
			"desc": "The name of the organization or individual that published the structure map."
		},
		{
			"name": "purpose",
			"order": 18,
			"type": "kCharacter",
			"subtype": "kSimplechar",
			"sublen": 100000000,
			"desc": "Explanation of why this structure map is needed and why it has been designed as it has."
		},
		{
			"name": "status",
			"order": 7,
			"type": "kCharacter",
			"subtype": "kSimplechar",
			"sublen": 100000000,
			"desc": "The status of this structure map. Enables tracking the life-cycle of the content."
		},
		{
			"name": "structure",
			"order": 20,
			"type": "kList",
			"subtype": "",
			"sublen": 0
		},
		{
			"name": "structure_",
			"order": 21,
			"type": "kObjectref",
			"subtype": "oStructureMapStructure",
			"sublen": 0,
			"desc": "A structure definition used by this map. The structure definition may describe instances that are converted, or the instances that are produced."
		},
		{
			"name": "title",
			"order": 6,
			"type": "kCharacter",
			"subtype": "kSimplechar",
			"sublen": 100000000,
			"desc": "A short, descriptive, user-friendly title for the structure map."
		},
		{
			"name": "url",
			"order": 1,
			"type": "kCharacter",
			"subtype": "kSimplechar",
			"sublen": 100000000,
			"desc": "An absolute URI that is used to identify this structure map when it is referenced in a specification, model, design or an instance; also called its canonical identifier. This SHOULD be globally unique and SHOULD be a literal address at which at which an a"
		},
		{
			"name": "useContext",
			"order": 14,
			"type": "kList",
			"subtype": "",
			"sublen": 0
		},
		{
			"name": "useContext_",
			"order": 15,
			"type": "kObjectref",
			"subtype": "oUsageContext",
			"sublen": 0,
			"desc": "The content was developed with a focus and intent of supporting the contexts that are listed. These contexts may be general categories (gender, age, ...) or may be references to specific programs (insurance plans, studies, ...) and may be used to assist w"
		},
		{
			"name": "version",
			"order": 4,
			"type": "kCharacter",
			"subtype": "kSimplechar",
			"sublen": 100000000,
			"desc": "The identifier that is used to identify this version of the structure map when it is referenced in a specification, model, design or instance. This is an arbitrary value managed by the structure map author and is not expected to be globally unique. For ex"
		}
	],
	"properties": {
		"collectperformancedata": false,
		"componenticon": 0,
		"componenttype": "kCompStoreHidden",
		"createdate": "2020-06-01 17:41:55",
		"desc": "A Map of relationships between 2 structures that can be used to transform data.",
		"editor": "",
		"editordata": "",
		"external": true,
		"issupercomponent": false,
		"moddate": "2020-06-01 17:57:24",
		"selfcontained": false,
		"showascheckedout": false,
		"userinfo": "",
		"version": ""
	}
}
