{
	"classtype": "kObjectclass",
	"internalversion": 3,
	"superclass": "fhir.FHIRBaseElement",
	"designtaskname": "",
	"cvardefs": [
		{
			"name": "cElements",
			"order": 1,
			"type": "kList",
			"subtype": "",
			"sublen": 0
		},
		{
			"name": "cElementsInited",
			"order": 2,
			"type": "kBoolean",
			"subtype": 0,
			"sublen": 0
		}
	],
	"ivardefs": [
		{
			"name": "contact",
			"order": 6,
			"type": "kList",
			"subtype": "",
			"sublen": 0
		},
		{
			"name": "contact_",
			"order": 7,
			"type": "kObjectref",
			"subtype": "oContactDetail",
			"sublen": 0,
			"desc": "Contact details to assist a user in finding and communicating with the publisher."
		},
		{
			"name": "date",
			"order": 4,
			"type": "kDate",
			"subtype": "kDatetime",
			"sublen": 0,
			"desc": "The date  (and optionally time) when the naming system was published. The date must change when the business version changes and it must change if the status code changes. In addition, it should change when the substantive content of the naming system cha"
		},
		{
			"name": "description",
			"order": 10,
			"type": "kCharacter",
			"subtype": "kSimplechar",
			"sublen": 100000000,
			"desc": "A free text natural language description of the naming system from a consumer's perspective. Details about what the namespace identifies including scope, granularity, version labeling, etc."
		},
		{
			"name": "jurisdiction",
			"order": 13,
			"type": "kList",
			"subtype": "",
			"sublen": 0
		},
		{
			"name": "jurisdiction_",
			"order": 14,
			"type": "kObjectref",
			"subtype": "oCodeableConcept",
			"sublen": 0,
			"desc": "A legal or geographic region in which the naming system is intended to be used."
		},
		{
			"name": "kind",
			"order": 3,
			"type": "kCharacter",
			"subtype": "kSimplechar",
			"sublen": 100000000,
			"desc": "Indicates the purpose for the naming system - what kinds of things does it make unique?"
		},
		{
			"name": "name",
			"order": 1,
			"type": "kCharacter",
			"subtype": "kSimplechar",
			"sublen": 100000000,
			"desc": "A natural language name identifying the naming system. This name should be usable as an identifier for the module by machine processing applications such as code generation."
		},
		{
			"name": "publisher",
			"order": 5,
			"type": "kCharacter",
			"subtype": "kSimplechar",
			"sublen": 100000000,
			"desc": "The name of the organization or individual that published the naming system."
		},
		{
			"name": "responsible",
			"order": 8,
			"type": "kCharacter",
			"subtype": "kSimplechar",
			"sublen": 100000000,
			"desc": "The name of the organization that is responsible for issuing identifiers or codes for this namespace and ensuring their non-collision."
		},
		{
			"name": "status",
			"order": 2,
			"type": "kCharacter",
			"subtype": "kSimplechar",
			"sublen": 100000000,
			"desc": "The status of this naming system. Enables tracking the life-cycle of the content."
		},
		{
			"name": "type",
			"order": 9,
			"type": "kObjectref",
			"subtype": "oCodeableConcept",
			"sublen": 0,
			"desc": "Categorizes a naming system for easier search by grouping related naming systems."
		},
		{
			"name": "uniqueId",
			"order": 16,
			"type": "kList",
			"subtype": "",
			"sublen": 0
		},
		{
			"name": "uniqueId_",
			"order": 17,
			"type": "kObjectref",
			"subtype": "oNamingSystemUniqueId",
			"sublen": 0,
			"desc": "Indicates how the system may be identified when referenced in electronic exchange."
		},
		{
			"name": "usage",
			"order": 15,
			"type": "kCharacter",
			"subtype": "kSimplechar",
			"sublen": 100000000,
			"desc": "Provides guidance on the use of the namespace, including the handling of formatting characters, use of upper vs. lower case, etc."
		},
		{
			"name": "useContext",
			"order": 11,
			"type": "kList",
			"subtype": "",
			"sublen": 0
		},
		{
			"name": "useContext_",
			"order": 12,
			"type": "kObjectref",
			"subtype": "oUsageContext",
			"sublen": 0,
			"desc": "The content was developed with a focus and intent of supporting the contexts that are listed. These contexts may be general categories (gender, age, ...) or may be references to specific programs (insurance plans, studies, ...) and may be used to assist w"
		}
	],
	"properties": {
		"collectperformancedata": false,
		"componenticon": 0,
		"componenttype": "kCompStoreHidden",
		"createdate": "2020-06-01 17:41:49",
		"desc": "A curated namespace that issues unique symbols within that namespace for the identification of concepts, people, devices, etc.  Represents a \"System\" used within the Identifier and Coding data types.",
		"editor": "",
		"editordata": "",
		"external": true,
		"issupercomponent": false,
		"moddate": "2020-06-01 17:57:25",
		"selfcontained": false,
		"showascheckedout": false,
		"userinfo": "",
		"version": ""
	}
}
