{
	"classtype": "kObjectclass",
	"internalversion": 3,
	"superclass": "fhir.FHIRBaseElement",
	"designtaskname": "",
	"cvardefs": [
		{
			"name": "cElements",
			"order": 1,
			"type": "kList",
			"subtype": "",
			"sublen": 0
		},
		{
			"name": "cElementsInited",
			"order": 2,
			"type": "kBoolean",
			"subtype": 0,
			"sublen": 0
		}
	],
	"ivardefs": [
		{
			"name": "date",
			"order": 1,
			"type": "kDate",
			"subtype": "kDate2000",
			"sublen": 0,
			"desc": "Date of an accident event  related to the products and services contained in the claim."
		},
		{
			"name": "type",
			"order": 2,
			"type": "kObjectref",
			"subtype": "oCodeableConcept",
			"sublen": 0,
			"desc": "The type or context of the accident event for the purposes of selection of potential insurance coverages and determination of coordination between insurers."
		}
	],
	"properties": {
		"collectperformancedata": false,
		"componenticon": 0,
		"componenttype": "kCompStoreHidden",
		"createdate": "2020-06-01 17:44:48",
		"desc": "Details of a accident which resulted in injuries which required the products and services listed in the claim.",
		"editor": "",
		"editordata": "",
		"external": true,
		"issupercomponent": false,
		"moddate": "2020-06-01 17:57:28",
		"selfcontained": false,
		"showascheckedout": false,
		"userinfo": "",
		"version": ""
	}
}
