[
	{
		"name": "$metadata",
		"ident": 0,
		"order": 1,
		"pvardefs": [

		],
		"lvardefs": [

		]
	},
	{
		"name": "$setupMetadata",
		"ident": 1,
		"order": 2,
		"pvardefs": [
			{
				"name": "pElements",
				"order": 1,
				"type": "kFieldreference",
				"subtype": 0,
				"sublen": 0,
				"param": 1
			}
		],
		"lvardefs": [

		]
	},
	{
		"name": "$construct",
		"ident": 2,
		"order": 3,
		"pvardefs": [

		],
		"lvardefs": [

		]
	},
	{
		"name": "$copyFrom",
		"ident": 3,
		"order": 4,
		"pvardefs": [

		],
		"lvardefs": [
			{
				"name": "itemRef",
				"order": 2,
				"type": "kItemref",
				"subtype": "",
				"sublen": 0
			},
			{
				"name": "list",
				"order": 1,
				"type": "kList",
				"subtype": "",
				"sublen": 0
			}
		]
	},
	{
		"name": "$cors",
		"ident": 4,
		"order": 5,
		"desc": "Returns: Server adds CORS headers when responding to requests - this enables javascript applications to use the server.",
		"pvardefs": [

		],
		"lvardefs": [

		]
	},
	{
		"name": "$cors.$assign",
		"ident": 5,
		"order": 6,
		"pvardefs": [
			{
				"name": "pValue",
				"order": 1,
				"type": "kBoolean",
				"subtype": 0,
				"sublen": 0,
				"param": 1,
				"desc": "Server adds CORS headers when responding to requests - this enables javascript applications to use the server."
			}
		],
		"lvardefs": [

		]
	},
	{
		"name": "$service",
		"ident": 6,
		"order": 7,
		"desc": "Returns: Types of security services that are supported/required by the system.",
		"pvardefs": [

		],
		"lvardefs": [

		]
	},
	{
		"name": "$addservice",
		"ident": 7,
		"order": 8,
		"desc": "Types of security services that are supported/required by the system.",
		"pvardefs": [
			{
				"name": "pValue",
				"order": 1,
				"type": "kObjectref",
				"subtype": "oCodeableConcept",
				"sublen": 0,
				"param": 1
			}
		],
		"lvardefs": [
			{
				"name": "objRef",
				"order": 2,
				"type": "kObjectref",
				"subtype": "oCodeableConcept",
				"sublen": 0,
				"desc": "Types of security services that are supported/required by the system."
			}
		]
	},
	{
		"name": "$description",
		"ident": 8,
		"order": 9,
		"desc": "Returns: General description of how security works.",
		"pvardefs": [

		],
		"lvardefs": [

		]
	},
	{
		"name": "$description.$assign",
		"ident": 9,
		"order": 10,
		"pvardefs": [
			{
				"name": "pValue",
				"order": 1,
				"type": "kCharacter",
				"subtype": "kSimplechar",
				"sublen": 100000000,
				"param": 1,
				"desc": "General description of how security works."
			}
		],
		"lvardefs": [

		]
	},
	{
		"name": "$certificate",
		"ident": 10,
		"order": 11,
		"desc": "Returns: Certificates associated with security profiles.",
		"pvardefs": [

		],
		"lvardefs": [

		]
	},
	{
		"name": "$addcertificate",
		"ident": 11,
		"order": 12,
		"desc": "Certificates associated with security profiles.",
		"pvardefs": [
			{
				"name": "pValue",
				"order": 1,
				"type": "kObjectref",
				"subtype": "oCapabilityStatementRestSecurityCertificate",
				"sublen": 0,
				"param": 1
			}
		],
		"lvardefs": [
			{
				"name": "objRef",
				"order": 2,
				"type": "kObjectref",
				"subtype": "oCapabilityStatementRestSecurityCertificate",
				"sublen": 0,
				"desc": "Certificates associated with security profiles."
			}
		]
	}
]
