{
	"classtype": "kObjectclass",
	"internalversion": 3,
	"superclass": "fhir.FHIRBaseElement",
	"designtaskname": "",
	"cvardefs": [
		{
			"name": "cElements",
			"order": 1,
			"type": "kList",
			"subtype": "",
			"sublen": 0
		},
		{
			"name": "cElementsInited",
			"order": 2,
			"type": "kBoolean",
			"subtype": 0,
			"sublen": 0
		}
	],
	"ivardefs": [
		{
			"name": "additive",
			"order": 3,
			"type": "kList",
			"subtype": "",
			"sublen": 0
		},
		{
			"name": "additive_",
			"order": 4,
			"type": "kObjectref",
			"subtype": "oReference",
			"sublen": 0,
			"desc": "Material used in the processing step."
		},
		{
			"name": "description",
			"order": 1,
			"type": "kCharacter",
			"subtype": "kSimplechar",
			"sublen": 100000000,
			"desc": "Textual description of procedure."
		},
		{
			"name": "procedure",
			"order": 2,
			"type": "kObjectref",
			"subtype": "oCodeableConcept",
			"sublen": 0,
			"desc": "A coded value specifying the procedure used to process the specimen."
		}
	],
	"properties": {
		"collectperformancedata": false,
		"componenticon": 0,
		"componenttype": "kCompStoreHidden",
		"createdate": "2020-06-01 17:45:01",
		"desc": "Details concerning processing and processing steps for the specimen.",
		"editor": "",
		"editordata": "",
		"external": true,
		"issupercomponent": false,
		"moddate": "2020-06-01 17:57:28",
		"selfcontained": false,
		"showascheckedout": false,
		"userinfo": "",
		"version": ""
	}
}
