[
	{
		"name": "$metadata",
		"ident": 0,
		"order": 1,
		"pvardefs": [

		],
		"lvardefs": [

		]
	},
	{
		"name": "$setupMetadata",
		"ident": 1,
		"order": 2,
		"pvardefs": [
			{
				"name": "pElements",
				"order": 1,
				"type": "kFieldreference",
				"subtype": 0,
				"sublen": 0,
				"param": 1
			}
		],
		"lvardefs": [

		]
	},
	{
		"name": "$construct",
		"ident": 2,
		"order": 3,
		"pvardefs": [

		],
		"lvardefs": [

		]
	},
	{
		"name": "$copyFrom",
		"ident": 3,
		"order": 4,
		"pvardefs": [

		],
		"lvardefs": [
			{
				"name": "itemRef",
				"order": 2,
				"type": "kItemref",
				"subtype": "",
				"sublen": 0
			},
			{
				"name": "list",
				"order": 1,
				"type": "kList",
				"subtype": "",
				"sublen": 0
			}
		]
	},
	{
		"name": "$role",
		"ident": 4,
		"order": 5,
		"desc": "Returns: Indicates specific responsibility of an individual within the care team, such as \"Primary care physician\", \"Trained social worker counselor\", \"Caregiver\", etc.",
		"pvardefs": [

		],
		"lvardefs": [

		]
	},
	{
		"name": "$role.$assign",
		"ident": 5,
		"order": 6,
		"pvardefs": [
			{
				"name": "pValue",
				"order": 1,
				"type": "kObjectref",
				"subtype": "oCodeableConcept",
				"sublen": 0,
				"param": 1,
				"desc": "Indicates specific responsibility of an individual within the care team, such as \"Primary care physician\", \"Trained social worker counselor\", \"Caregiver\", etc."
			}
		],
		"lvardefs": [

		]
	},
	{
		"name": "$member",
		"ident": 6,
		"order": 7,
		"desc": "Returns: The specific person or organization who is participating/expected to participate in the care team.",
		"pvardefs": [

		],
		"lvardefs": [

		]
	},
	{
		"name": "$member.$assign",
		"ident": 7,
		"order": 8,
		"pvardefs": [
			{
				"name": "pValue",
				"order": 1,
				"type": "kObjectref",
				"subtype": "oReference",
				"sublen": 0,
				"param": 1,
				"desc": "The specific person or organization who is participating/expected to participate in the care team."
			}
		],
		"lvardefs": [

		]
	},
	{
		"name": "$onBehalfOf",
		"ident": 8,
		"order": 9,
		"desc": "Returns: The organization of the practitioner.",
		"pvardefs": [

		],
		"lvardefs": [

		]
	},
	{
		"name": "$onBehalfOf.$assign",
		"ident": 9,
		"order": 10,
		"pvardefs": [
			{
				"name": "pValue",
				"order": 1,
				"type": "kObjectref",
				"subtype": "oReference",
				"sublen": 0,
				"param": 1,
				"desc": "The organization of the practitioner."
			}
		],
		"lvardefs": [

		]
	},
	{
		"name": "$period",
		"ident": 10,
		"order": 11,
		"desc": "Returns: Indicates when the specific member or organization did (or is intended to) come into effect and end.",
		"pvardefs": [

		],
		"lvardefs": [

		]
	},
	{
		"name": "$period.$assign",
		"ident": 11,
		"order": 12,
		"pvardefs": [
			{
				"name": "pValue",
				"order": 1,
				"type": "kObjectref",
				"subtype": "oPeriod",
				"sublen": 0,
				"param": 1,
				"desc": "Indicates when the specific member or organization did (or is intended to) come into effect and end."
			}
		],
		"lvardefs": [

		]
	}
]
