[
	{
		"name": "$resourceType",
		"ident": 0,
		"order": 1,
		"desc": "Returns the FHIR type name for this instance",
		"pvardefs": [

		],
		"lvardefs": [

		]
	},
	{
		"name": "$metadata",
		"ident": 1,
		"order": 2,
		"pvardefs": [

		],
		"lvardefs": [

		]
	},
	{
		"name": "$setupMetadata",
		"ident": 2,
		"order": 3,
		"pvardefs": [
			{
				"name": "pElements",
				"order": 1,
				"type": "kFieldreference",
				"subtype": 0,
				"sublen": 0,
				"param": 1
			}
		],
		"lvardefs": [

		]
	},
	{
		"name": "$construct",
		"ident": 3,
		"order": 4,
		"pvardefs": [

		],
		"lvardefs": [

		]
	},
	{
		"name": "$copyFrom",
		"ident": 4,
		"order": 5,
		"pvardefs": [

		],
		"lvardefs": [
			{
				"name": "itemRef",
				"order": 2,
				"type": "kItemref",
				"subtype": "",
				"sublen": 0
			},
			{
				"name": "list",
				"order": 1,
				"type": "kList",
				"subtype": "",
				"sublen": 0
			}
		]
	},
	{
		"name": "$url",
		"ident": 5,
		"order": 6,
		"desc": "Returns: An absolute URI that is used to identify this capability statement when it is referenced in a specification, model, design or an instance. This SHALL be a URL, SHOULD be globally unique, and SHOULD be an address at which this capability statement is (or will be) published. The URL SHOULD include the major version of the capability statement. For more information see [Technical and Business Versions](resource.html#versions).",
		"pvardefs": [

		],
		"lvardefs": [

		]
	},
	{
		"name": "$url.$assign",
		"ident": 6,
		"order": 7,
		"pvardefs": [
			{
				"name": "pValue",
				"order": 1,
				"type": "kCharacter",
				"subtype": "kSimplechar",
				"sublen": 100000000,
				"param": 1,
				"desc": "An absolute URI that is used to identify this capability statement when it is referenced in a specification, model, design or an instance. This SHALL be a URL, SHOULD be globally unique, and SHOULD be an address at which this capability statement is (or w"
			}
		],
		"lvardefs": [

		]
	},
	{
		"name": "$::version",
		"ident": 7,
		"order": 8,
		"desc": "Returns: The identifier that is used to identify this version of the capability statement when it is referenced in a specification, model, design or instance. This is an arbitrary value managed by the capability statement author and is not expected to be globally unique. For example, it might be a timestamp (e.g. yyyymmdd) if a managed version is not available. There is also no expectation that versions can be placed in a lexicographical sequence.",
		"pvardefs": [

		],
		"lvardefs": [

		]
	},
	{
		"name": "$::version.$assign",
		"ident": 8,
		"order": 9,
		"pvardefs": [
			{
				"name": "pValue",
				"order": 1,
				"type": "kCharacter",
				"subtype": "kSimplechar",
				"sublen": 100000000,
				"param": 1,
				"desc": "The identifier that is used to identify this version of the capability statement when it is referenced in a specification, model, design or instance. This is an arbitrary value managed by the capability statement author and is not expected to be globally "
			}
		],
		"lvardefs": [

		]
	},
	{
		"name": "$::name",
		"ident": 9,
		"order": 10,
		"desc": "Returns: A natural language name identifying the capability statement. This name should be usable as an identifier for the module by machine processing applications such as code generation.",
		"pvardefs": [

		],
		"lvardefs": [

		]
	},
	{
		"name": "$::name.$assign",
		"ident": 10,
		"order": 11,
		"pvardefs": [
			{
				"name": "pValue",
				"order": 1,
				"type": "kCharacter",
				"subtype": "kSimplechar",
				"sublen": 100000000,
				"param": 1,
				"desc": "A natural language name identifying the capability statement. This name should be usable as an identifier for the module by machine processing applications such as code generation."
			}
		],
		"lvardefs": [

		]
	},
	{
		"name": "$title",
		"ident": 11,
		"order": 12,
		"desc": "Returns: A short, descriptive, user-friendly title for the capability statement.",
		"pvardefs": [

		],
		"lvardefs": [

		]
	},
	{
		"name": "$title.$assign",
		"ident": 12,
		"order": 13,
		"pvardefs": [
			{
				"name": "pValue",
				"order": 1,
				"type": "kCharacter",
				"subtype": "kSimplechar",
				"sublen": 100000000,
				"param": 1,
				"desc": "A short, descriptive, user-friendly title for the capability statement."
			}
		],
		"lvardefs": [

		]
	},
	{
		"name": "$status",
		"ident": 13,
		"order": 14,
		"desc": "Returns: The status of this capability statement. Enables tracking the life-cycle of the content.",
		"pvardefs": [

		],
		"lvardefs": [

		]
	},
	{
		"name": "$status.$assign",
		"ident": 14,
		"order": 15,
		"pvardefs": [
			{
				"name": "pValue",
				"order": 1,
				"type": "kCharacter",
				"subtype": "kSimplechar",
				"sublen": 100000000,
				"param": 1,
				"desc": "The status of this capability statement. Enables tracking the life-cycle of the content."
			}
		],
		"lvardefs": [

		]
	},
	{
		"name": "$experimental",
		"ident": 15,
		"order": 16,
		"desc": "Returns: A boolean value to indicate that this capability statement is authored for testing purposes (or education/evaluation/marketing), and is not intended to be used for genuine usage.",
		"pvardefs": [

		],
		"lvardefs": [

		]
	},
	{
		"name": "$experimental.$assign",
		"ident": 16,
		"order": 17,
		"pvardefs": [
			{
				"name": "pValue",
				"order": 1,
				"type": "kBoolean",
				"subtype": 0,
				"sublen": 0,
				"param": 1,
				"desc": "A boolean value to indicate that this capability statement is authored for testing purposes (or education/evaluation/marketing), and is not intended to be used for genuine usage."
			}
		],
		"lvardefs": [

		]
	},
	{
		"name": "$date",
		"ident": 17,
		"order": 18,
		"desc": "Returns: The date  (and optionally time) when the capability statement was published. The date must change if and when the business version changes and it must change if the status code changes. In addition, it should change when the substantive content of the capability statement changes.",
		"pvardefs": [

		],
		"lvardefs": [

		]
	},
	{
		"name": "$date.$assign",
		"ident": 18,
		"order": 19,
		"pvardefs": [
			{
				"name": "pValue",
				"order": 1,
				"type": "kDate",
				"subtype": "kDatetime",
				"sublen": 0,
				"param": 1,
				"desc": "The date  (and optionally time) when the capability statement was published. The date must change if and when the business version changes and it must change if the status code changes. In addition, it should change when the substantive content of the cap"
			}
		],
		"lvardefs": [

		]
	},
	{
		"name": "$publisher",
		"ident": 19,
		"order": 20,
		"desc": "Returns: The name of the individual or organization that published the capability statement.",
		"pvardefs": [

		],
		"lvardefs": [

		]
	},
	{
		"name": "$publisher.$assign",
		"ident": 20,
		"order": 21,
		"pvardefs": [
			{
				"name": "pValue",
				"order": 1,
				"type": "kCharacter",
				"subtype": "kSimplechar",
				"sublen": 100000000,
				"param": 1,
				"desc": "The name of the individual or organization that published the capability statement."
			}
		],
		"lvardefs": [

		]
	},
	{
		"name": "$contact",
		"ident": 21,
		"order": 22,
		"desc": "Returns: Contact details to assist a user in finding and communicating with the publisher.",
		"pvardefs": [

		],
		"lvardefs": [

		]
	},
	{
		"name": "$addcontact",
		"ident": 22,
		"order": 23,
		"desc": "Contact details to assist a user in finding and communicating with the publisher.",
		"pvardefs": [
			{
				"name": "pValue",
				"order": 1,
				"type": "kObjectref",
				"subtype": "oContactDetail",
				"sublen": 0,
				"param": 1
			}
		],
		"lvardefs": [
			{
				"name": "objRef",
				"order": 2,
				"type": "kObjectref",
				"subtype": "oContactDetail",
				"sublen": 0,
				"desc": "Contact details to assist a user in finding and communicating with the publisher."
			}
		]
	},
	{
		"name": "$description",
		"ident": 23,
		"order": 24,
		"desc": "Returns: A free text natural language description of the capability statement from a consumer's perspective. Typically, this is used when the capability statement describes a desired rather than an actual solution, for example as a formal expression of requirements as part of an RFP.",
		"pvardefs": [

		],
		"lvardefs": [

		]
	},
	{
		"name": "$description.$assign",
		"ident": 24,
		"order": 25,
		"pvardefs": [
			{
				"name": "pValue",
				"order": 1,
				"type": "kCharacter",
				"subtype": "kSimplechar",
				"sublen": 100000000,
				"param": 1,
				"desc": "A free text natural language description of the capability statement from a consumer's perspective. Typically, this is used when the capability statement describes a desired rather than an actual solution, for example as a formal expression of requirement"
			}
		],
		"lvardefs": [

		]
	},
	{
		"name": "$useContext",
		"ident": 25,
		"order": 26,
		"desc": "Returns: The content was developed with a focus and intent of supporting the contexts that are listed. These terms may be used to assist with indexing and searching for appropriate capability statement instances.",
		"pvardefs": [

		],
		"lvardefs": [

		]
	},
	{
		"name": "$adduseContext",
		"ident": 26,
		"order": 27,
		"desc": "The content was developed with a focus and intent of supporting the contexts that are listed. These terms may be used to assist with indexing and searching for appropriate capability statement instances.",
		"pvardefs": [
			{
				"name": "pValue",
				"order": 1,
				"type": "kObjectref",
				"subtype": "oUsageContext",
				"sublen": 0,
				"param": 1
			}
		],
		"lvardefs": [
			{
				"name": "objRef",
				"order": 2,
				"type": "kObjectref",
				"subtype": "oUsageContext",
				"sublen": 0,
				"desc": "The content was developed with a focus and intent of supporting the contexts that are listed. These terms may be used to assist with indexing and searching for appropriate capability statement instances."
			}
		]
	},
	{
		"name": "$jurisdiction",
		"ident": 27,
		"order": 28,
		"desc": "Returns: A legal or geographic region in which the capability statement is intended to be used.",
		"pvardefs": [

		],
		"lvardefs": [

		]
	},
	{
		"name": "$addjurisdiction",
		"ident": 28,
		"order": 29,
		"desc": "A legal or geographic region in which the capability statement is intended to be used.",
		"pvardefs": [
			{
				"name": "pValue",
				"order": 1,
				"type": "kObjectref",
				"subtype": "oCodeableConcept",
				"sublen": 0,
				"param": 1
			}
		],
		"lvardefs": [
			{
				"name": "objRef",
				"order": 2,
				"type": "kObjectref",
				"subtype": "oCodeableConcept",
				"sublen": 0,
				"desc": "A legal or geographic region in which the capability statement is intended to be used."
			}
		]
	},
	{
		"name": "$purpose",
		"ident": 29,
		"order": 30,
		"desc": "Returns: Explaination of why this capability statement is needed and why it has been designed as it has.",
		"pvardefs": [

		],
		"lvardefs": [

		]
	},
	{
		"name": "$purpose.$assign",
		"ident": 30,
		"order": 31,
		"pvardefs": [
			{
				"name": "pValue",
				"order": 1,
				"type": "kCharacter",
				"subtype": "kSimplechar",
				"sublen": 100000000,
				"param": 1,
				"desc": "Explaination of why this capability statement is needed and why it has been designed as it has."
			}
		],
		"lvardefs": [

		]
	},
	{
		"name": "$copyright",
		"ident": 31,
		"order": 32,
		"desc": "Returns: A copyright statement relating to the capability statement and/or its contents. Copyright statements are generally legal restrictions on the use and publishing of the capability statement.",
		"pvardefs": [

		],
		"lvardefs": [

		]
	},
	{
		"name": "$copyright.$assign",
		"ident": 32,
		"order": 33,
		"pvardefs": [
			{
				"name": "pValue",
				"order": 1,
				"type": "kCharacter",
				"subtype": "kSimplechar",
				"sublen": 100000000,
				"param": 1,
				"desc": "A copyright statement relating to the capability statement and/or its contents. Copyright statements are generally legal restrictions on the use and publishing of the capability statement."
			}
		],
		"lvardefs": [

		]
	},
	{
		"name": "$kind",
		"ident": 33,
		"order": 34,
		"desc": "Returns: The way that this statement is intended to be used, to describe an actual running instance of software, a particular product (kind not instance of software) or a class of implementation (e.g. a desired purchase).",
		"pvardefs": [

		],
		"lvardefs": [

		]
	},
	{
		"name": "$kind.$assign",
		"ident": 34,
		"order": 35,
		"pvardefs": [
			{
				"name": "pValue",
				"order": 1,
				"type": "kCharacter",
				"subtype": "kSimplechar",
				"sublen": 100000000,
				"param": 1,
				"desc": "The way that this statement is intended to be used, to describe an actual running instance of software, a particular product (kind not instance of software) or a class of implementation (e.g. a desired purchase)."
			}
		],
		"lvardefs": [

		]
	},
	{
		"name": "$instantiates",
		"ident": 35,
		"order": 36,
		"desc": "Returns: Reference to a canonical URL of another CapabilityStatement that this software implements or uses. This capability statement is a published API description that corresponds to a business service. The rest of the capability statement does not need to repeat the details of the referenced resource, but can do so.",
		"pvardefs": [

		],
		"lvardefs": [

		]
	},
	{
		"name": "$addinstantiates",
		"ident": 36,
		"order": 37,
		"desc": "Reference to a canonical URL of another CapabilityStatement that this software implements or uses. This capability statement is a published API description that corresponds to a business service. The rest of the capability statement does not need to repeat the details of the referenced resource, but can do so.",
		"pvardefs": [
			{
				"name": "pValue",
				"order": 1,
				"type": "kCharacter",
				"subtype": "kSimplechar",
				"sublen": 100000000,
				"param": 1,
				"desc": "Reference to a canonical URL of another CapabilityStatement that this software implements or uses. This capability statement is a published API description that corresponds to a business service. The rest of the capability statement does not need to repea"
			}
		],
		"lvardefs": [

		]
	},
	{
		"name": "$software",
		"ident": 37,
		"order": 38,
		"desc": "Returns: Software that is covered by this capability statement.  It is used when the capability statement describes the capabilities of a particular software version, independent of an installation.",
		"pvardefs": [

		],
		"lvardefs": [

		]
	},
	{
		"name": "$software.$assign",
		"ident": 38,
		"order": 39,
		"pvardefs": [
			{
				"name": "pValue",
				"order": 1,
				"type": "kObjectref",
				"subtype": "oCapabilityStatementSoftware",
				"sublen": 0,
				"param": 1,
				"desc": "Software that is covered by this capability statement.  It is used when the capability statement describes the capabilities of a particular software version, independent of an installation."
			}
		],
		"lvardefs": [

		]
	},
	{
		"name": "$implementation",
		"ident": 39,
		"order": 40,
		"desc": "Returns: Identifies a specific implementation instance that is described by the capability statement - i.e. a particular installation, rather than the capabilities of a software program.",
		"pvardefs": [

		],
		"lvardefs": [

		]
	},
	{
		"name": "$implementation.$assign",
		"ident": 40,
		"order": 41,
		"pvardefs": [
			{
				"name": "pValue",
				"order": 1,
				"type": "kObjectref",
				"subtype": "oCapabilityStatementImplementation",
				"sublen": 0,
				"param": 1,
				"desc": "Identifies a specific implementation instance that is described by the capability statement - i.e. a particular installation, rather than the capabilities of a software program."
			}
		],
		"lvardefs": [

		]
	},
	{
		"name": "$fhirVersion",
		"ident": 41,
		"order": 42,
		"desc": "Returns: The version of the FHIR specification on which this capability statement is based.",
		"pvardefs": [

		],
		"lvardefs": [

		]
	},
	{
		"name": "$fhirVersion.$assign",
		"ident": 42,
		"order": 43,
		"pvardefs": [
			{
				"name": "pValue",
				"order": 1,
				"type": "kCharacter",
				"subtype": "kSimplechar",
				"sublen": 100000000,
				"param": 1,
				"desc": "The version of the FHIR specification on which this capability statement is based."
			}
		],
		"lvardefs": [

		]
	},
	{
		"name": "$acceptUnknown",
		"ident": 43,
		"order": 44,
		"desc": "Returns: A code that indicates whether the application accepts unknown elements or extensions when reading resources.",
		"pvardefs": [

		],
		"lvardefs": [

		]
	},
	{
		"name": "$acceptUnknown.$assign",
		"ident": 44,
		"order": 45,
		"pvardefs": [
			{
				"name": "pValue",
				"order": 1,
				"type": "kCharacter",
				"subtype": "kSimplechar",
				"sublen": 100000000,
				"param": 1,
				"desc": "A code that indicates whether the application accepts unknown elements or extensions when reading resources."
			}
		],
		"lvardefs": [

		]
	},
	{
		"name": "$format",
		"ident": 45,
		"order": 46,
		"desc": "Returns: A list of the formats supported by this implementation using their content types.",
		"pvardefs": [

		],
		"lvardefs": [

		]
	},
	{
		"name": "$addformat",
		"ident": 46,
		"order": 47,
		"desc": "A list of the formats supported by this implementation using their content types.",
		"pvardefs": [
			{
				"name": "pValue",
				"order": 1,
				"type": "kCharacter",
				"subtype": "kSimplechar",
				"sublen": 100000000,
				"param": 1,
				"desc": "A list of the formats supported by this implementation using their content types."
			}
		],
		"lvardefs": [

		]
	},
	{
		"name": "$patchFormat",
		"ident": 47,
		"order": 48,
		"desc": "Returns: A list of the patch formats supported by this implementation using their content types.",
		"pvardefs": [

		],
		"lvardefs": [

		]
	},
	{
		"name": "$addpatchFormat",
		"ident": 48,
		"order": 49,
		"desc": "A list of the patch formats supported by this implementation using their content types.",
		"pvardefs": [
			{
				"name": "pValue",
				"order": 1,
				"type": "kCharacter",
				"subtype": "kSimplechar",
				"sublen": 100000000,
				"param": 1,
				"desc": "A list of the patch formats supported by this implementation using their content types."
			}
		],
		"lvardefs": [

		]
	},
	{
		"name": "$implementationGuide",
		"ident": 49,
		"order": 50,
		"desc": "Returns: A list of implementation guides that the server does (or should) support in their entirety.",
		"pvardefs": [

		],
		"lvardefs": [

		]
	},
	{
		"name": "$addimplementationGuide",
		"ident": 50,
		"order": 51,
		"desc": "A list of implementation guides that the server does (or should) support in their entirety.",
		"pvardefs": [
			{
				"name": "pValue",
				"order": 1,
				"type": "kCharacter",
				"subtype": "kSimplechar",
				"sublen": 100000000,
				"param": 1,
				"desc": "A list of implementation guides that the server does (or should) support in their entirety."
			}
		],
		"lvardefs": [

		]
	},
	{
		"name": "$profile",
		"ident": 51,
		"order": 52,
		"desc": "Returns: A list of profiles that represent different use cases supported by the system. For a server, \"supported by the system\" means the system hosts/produces a set of resources that are conformant to a particular profile, and allows clients that use its services to search using this profile and to find appropriate data. For a client, it means the system will search by this profile and process data according to the guidance implicit in the profile. See further discussion in [Using Profiles](profiling.html#profile-uses).",
		"pvardefs": [

		],
		"lvardefs": [

		]
	},
	{
		"name": "$addprofile",
		"ident": 52,
		"order": 53,
		"desc": "A list of profiles that represent different use cases supported by the system. For a server, \"supported by the system\" means the system hosts/produces a set of resources that are conformant to a particular profile, and allows clients that use its services to search using this profile and to find appropriate data. For a client, it means the system will search by this profile and process data according to the guidance implicit in the profile. See further discussion in [Using Profiles](profiling.html#profile-uses).",
		"pvardefs": [
			{
				"name": "pValue",
				"order": 1,
				"type": "kObjectref",
				"subtype": "oReference",
				"sublen": 0,
				"param": 1
			}
		],
		"lvardefs": [
			{
				"name": "objRef",
				"order": 2,
				"type": "kObjectref",
				"subtype": "oReference",
				"sublen": 0,
				"desc": "A list of profiles that represent different use cases supported by the system. For a server, \"supported by the system\" means the system hosts/produces a set of resources that are conformant to a particular profile, and allows clients that use its services"
			}
		]
	},
	{
		"name": "$rest",
		"ident": 53,
		"order": 54,
		"desc": "Returns: A definition of the restful capabilities of the solution, if any.",
		"pvardefs": [

		],
		"lvardefs": [

		]
	},
	{
		"name": "$addrest",
		"ident": 54,
		"order": 55,
		"desc": "A definition of the restful capabilities of the solution, if any.",
		"pvardefs": [
			{
				"name": "pValue",
				"order": 1,
				"type": "kObjectref",
				"subtype": "oCapabilityStatementRest",
				"sublen": 0,
				"param": 1
			}
		],
		"lvardefs": [
			{
				"name": "objRef",
				"order": 2,
				"type": "kObjectref",
				"subtype": "oCapabilityStatementRest",
				"sublen": 0,
				"desc": "A definition of the restful capabilities of the solution, if any."
			}
		]
	},
	{
		"name": "$messaging",
		"ident": 55,
		"order": 56,
		"desc": "Returns: A description of the messaging capabilities of the solution.",
		"pvardefs": [

		],
		"lvardefs": [

		]
	},
	{
		"name": "$addmessaging",
		"ident": 56,
		"order": 57,
		"desc": "A description of the messaging capabilities of the solution.",
		"pvardefs": [
			{
				"name": "pValue",
				"order": 1,
				"type": "kObjectref",
				"subtype": "oCapabilityStatementMessaging",
				"sublen": 0,
				"param": 1
			}
		],
		"lvardefs": [
			{
				"name": "objRef",
				"order": 2,
				"type": "kObjectref",
				"subtype": "oCapabilityStatementMessaging",
				"sublen": 0,
				"desc": "A description of the messaging capabilities of the solution."
			}
		]
	},
	{
		"name": "$document",
		"ident": 57,
		"order": 58,
		"desc": "Returns: A document definition.",
		"pvardefs": [

		],
		"lvardefs": [

		]
	},
	{
		"name": "$adddocument",
		"ident": 58,
		"order": 59,
		"desc": "A document definition.",
		"pvardefs": [
			{
				"name": "pValue",
				"order": 1,
				"type": "kObjectref",
				"subtype": "oCapabilityStatementDocument",
				"sublen": 0,
				"param": 1
			}
		],
		"lvardefs": [
			{
				"name": "objRef",
				"order": 2,
				"type": "kObjectref",
				"subtype": "oCapabilityStatementDocument",
				"sublen": 0,
				"desc": "A document definition."
			}
		]
	}
]
